peerfeedback/__init__.py
peerfeedback/input.py
peerfeedback/interfaces.py
peerfeedback/matcher.py
peerfeedback/output.py
peerfeedback-0.1.0.dist-info/entry_points.txt
peerfeedback-0.1.0.dist-info/LICENSE
peerfeedback-0.1.0.dist-info/WHEEL
peerfeedback-0.1.0.dist-info/METADATA
peerfeedback-0.1.0.dist-info/RECORD
