Metadata-Version: 2.1
Name: peerfeedback
Version: 0.1.0
Summary: 
License: GPL-3.0-or-later
Author: Alexander Graul
Author-email: mail@agraul.de
Requires-Python: >=3.8,<4.0
Classifier: License :: OSI Approved :: GNU General Public License v3 or later (GPLv3+)
Classifier: Programming Language :: Python :: 3
Classifier: Programming Language :: Python :: 3.8
Requires-Dist: pandas (>=1.1.3,<2.0.0)
Requires-Dist: xlrd (>=1.2.0,<2.0.0)
Requires-Dist: xlsxwriter (>=1.3.7,<2.0.0)
